[
  {
    "discussion_id": "396113348",
    "pr_number": 264,
    "pr_file": "test/helpers/render-to-string.ts",
    "created_at": "2020-03-22T16:29:44+00:00",
    "commented_code": "}\n }\n \n-export default (node, {columns} = {}) => {\n+const renderToString: (\n+\tnode: ReactNode,\n+\toptions?: { columns?: number }",
    "repo_full_name": "vadimdemedes/ink",
    "discussion_comments": [
      {
        "comment_id": "396113348",
        "repo_full_name": "vadimdemedes/ink",
        "pr_number": 264,
        "pr_file": "test/helpers/render-to-string.ts",
        "discussion_id": "396113348",
        "commented_code": "@@ -16,14 +19,20 @@ class Stream {\n \t}\n }\n \n-export default (node, {columns} = {}) => {\n+const renderToString: (\n+\tnode: ReactNode,\n+\toptions?: { columns?: number }",
        "comment_created_at": "2020-03-22T16:29:44+00:00",
        "comment_author": "sindresorhus",
        "comment_body": "```suggestion\r\n\toptions?: {\r\n\t\tcolumns?: number\r\n\t}\r\n```",
        "pr_file_module": null
      }
    ]
  },
  {
    "discussion_id": "324497870",
    "pr_number": 227,
    "pr_file": "index.d.ts",
    "created_at": "2019-09-16T02:39:02+00:00",
    "commented_code": "export type Unmount = () => void;\n \n+/**\n+ * Hook that calls inputHandler callback with input that program received.",
    "repo_full_name": "vadimdemedes/ink",
    "discussion_comments": [
      {
        "comment_id": "324497870",
        "repo_full_name": "vadimdemedes/ink",
        "pr_number": 227,
        "pr_file": "index.d.ts",
        "discussion_id": "324497870",
        "commented_code": "@@ -44,6 +44,21 @@ export type Instance = {\n \n export type Unmount = () => void;\n \n+/**\n+ * Hook that calls inputHandler callback with input that program received.",
        "comment_created_at": "2019-09-16T02:39:02+00:00",
        "comment_author": "sindresorhus",
        "comment_body": "```suggestion\r\n * Hook that calls the `inputHandler` callback with the input that the program received.\r\n```",
        "pr_file_module": null
      },
      {
        "comment_id": "324511367",
        "repo_full_name": "vadimdemedes/ink",
        "pr_number": 227,
        "pr_file": "index.d.ts",
        "discussion_id": "324497870",
        "commented_code": "@@ -44,6 +44,21 @@ export type Instance = {\n \n export type Unmount = () => void;\n \n+/**\n+ * Hook that calls inputHandler callback with input that program received.",
        "comment_created_at": "2019-09-16T05:09:37+00:00",
        "comment_author": "sindresorhus",
        "comment_body": "I would clarify when the inputHandler is called. It's not clear whether it's for each keypress, each line, or something else. Also mention the paste thing.",
        "pr_file_module": null
      }
    ]
  }
]