[
  {
    "discussion_id": "2009929716",
    "pr_number": 6143,
    "pr_file": "packages/shared/prisma/migrations/20250324104355_add_blobstorage_integration_table/migration.sql",
    "created_at": "2025-03-24T10:48:15+00:00",
    "commented_code": "+-- CreateTable\n+CREATE TABLE \"blob_storage_integrations\" (\n+    \"project_id\" TEXT NOT NULL,\n+    \"bucket_name\" TEXT NOT NULL,\n+    \"prefix\" TEXT NOT NULL,\n+    \"access_key_id\" TEXT NOT NULL,\n+    \"secret_access_key\" TEXT NOT NULL,",
    "repo_full_name": "langfuse/langfuse",
    "discussion_comments": [
      {
        "comment_id": "2009929716",
        "repo_full_name": "langfuse/langfuse",
        "pr_number": 6143,
        "pr_file": "packages/shared/prisma/migrations/20250324104355_add_blobstorage_integration_table/migration.sql",
        "discussion_id": "2009929716",
        "commented_code": "@@ -0,0 +1,21 @@\n+-- CreateTable\n+CREATE TABLE \"blob_storage_integrations\" (\n+    \"project_id\" TEXT NOT NULL,\n+    \"bucket_name\" TEXT NOT NULL,\n+    \"prefix\" TEXT NOT NULL,\n+    \"access_key_id\" TEXT NOT NULL,\n+    \"secret_access_key\" TEXT NOT NULL,",
        "comment_created_at": "2025-03-24T10:48:15+00:00",
        "comment_author": "ellipsis-dev[bot]",
        "comment_body": "Storing sensitive fields like `secret_access_key` in plain text in the DB can be a security risk. Consider using encryption or secure storage mechanisms.",
        "pr_file_module": null
      }
    ]
  }
]