[
  {
    "discussion_id": "1069858512",
    "pr_number": 4803,
    "pr_file": "examples/solid/solid-start/src/routes/index.tsx",
    "created_at": "2023-01-13T18:45:46+00:00",
    "commented_code": "+import { Title } from 'solid-start'\n+import { createQuery, useQueryClient } from '@tanstack/solid-query'\n+import { createSignal, For, Suspense } from 'solid-js'\n+import { isServer } from 'solid-js/web'\n+\n+interface PostData {\n+  userId: number\n+  id: number\n+  title: string\n+  body: string\n+}\n+\n+export default function Home() {\n+  const [postId, setPostId] = createSignal(1)\n+\n+  const query = createQuery(() => ({\n+    queryKey: ['posts', postId()],\n+    queryFn: async () => {\n+      const response = await fetch(\n+        'https://jsonplaceholder.typicode.com/posts/' + postId(),\n+      ).then((res) => res.json())\n+      return [response] as PostData[]\n+    },\n+  }))\n+\n+  return (\n+    <main>\n+      <Title>Solid Query v5</Title>\n+      <h1>Solid Query v5</h1>\n+      <p>\n+        This is just a dev release for demo. Please dont use it in production\n+        yet. Also this package will be deprecated as soon as features are live\n+        on @tanstack/query\n+      </p>\n+      <div>\n+        <button\n+          onClick={() => {\n+            setPostId((id) => (id === 1 ? 1 : id - 1))\n+          }}\n+        >\n+          Previous Page\n+        </button>\n+        <button\n+          onClick={() => {\n+            setPostId((id) => (id === 100 ? 100 : id + 1))\n+          }}\n+        >\n+          Next Page\n+        </button>\n+      </div>\n+      <Suspense>",
    "repo_full_name": "TanStack/query",
    "discussion_comments": [
      {
        "comment_id": "1069858512",
        "repo_full_name": "TanStack/query",
        "pr_number": 4803,
        "pr_file": "examples/solid/solid-start/src/routes/index.tsx",
        "discussion_id": "1069858512",
        "commented_code": "@@ -0,0 +1,63 @@\n+import { Title } from 'solid-start'\n+import { createQuery, useQueryClient } from '@tanstack/solid-query'\n+import { createSignal, For, Suspense } from 'solid-js'\n+import { isServer } from 'solid-js/web'\n+\n+interface PostData {\n+  userId: number\n+  id: number\n+  title: string\n+  body: string\n+}\n+\n+export default function Home() {\n+  const [postId, setPostId] = createSignal(1)\n+\n+  const query = createQuery(() => ({\n+    queryKey: ['posts', postId()],\n+    queryFn: async () => {\n+      const response = await fetch(\n+        'https://jsonplaceholder.typicode.com/posts/' + postId(),\n+      ).then((res) => res.json())\n+      return [response] as PostData[]\n+    },\n+  }))\n+\n+  return (\n+    <main>\n+      <Title>Solid Query v5</Title>\n+      <h1>Solid Query v5</h1>\n+      <p>\n+        This is just a dev release for demo. Please dont use it in production\n+        yet. Also this package will be deprecated as soon as features are live\n+        on @tanstack/query\n+      </p>\n+      <div>\n+        <button\n+          onClick={() => {\n+            setPostId((id) => (id === 1 ? 1 : id - 1))\n+          }}\n+        >\n+          Previous Page\n+        </button>\n+        <button\n+          onClick={() => {\n+            setPostId((id) => (id === 100 ? 100 : id + 1))\n+          }}\n+        >\n+          Next Page\n+        </button>\n+      </div>\n+      <Suspense>",
        "comment_created_at": "2023-01-13T18:45:46+00:00",
        "comment_author": "marbemac",
        "comment_body": "I'm not sure that this `Suspense` boundary is accomplishing anything? Since the resource is created outside of the boundary, up on line 16, I believe that the suspense boundary that is catching the resource is actually the root one in `root.tsx`.\r\n\r\nCan see this more clearly when you adjust `entry-server.tsx` to use `renderStream`, and turn off javascript to see which boundary actually catches the query on the server render:\r\n\r\n<img width=\"451\" alt=\"Screenshot 2023-01-13 at 1 41 41 PM\" src=\"https://user-images.githubusercontent.com/847542/212395038-1486b745-e1ac-4f42-9118-2399a10c0b2f.png\">\r\n\r\nA better example might be to move the query into a separate posts component, so that one can see the streaming magic and suspense boundary at work, which is SO cool :):\r\n\r\n<img width=\"1549\" alt=\"Screenshot 2023-01-13 at 1 44 20 PM\" src=\"https://user-images.githubusercontent.com/847542/212395552-d5f65bb7-1c8b-4648-9262-acfacd613c92.png\">\r\n\r\nAnd streaming shows off nicely - look at all that blue:\r\n\r\n<img width=\"1728\" alt=\"Screenshot 2023-01-13 at 1 47 16 PM\" src=\"https://user-images.githubusercontent.com/847542/212396195-c0ec3dcc-7c52-4dfd-93e9-a879651b7a9d.png\">\r\n\r\nExample adjustment to this file:\r\n\r\n```tsx\r\nimport { Title } from 'solid-start'\r\nimport { createQuery } from '@tanstack/solid-query'\r\nimport { createSignal, For, Suspense } from 'solid-js'\r\nimport type { Accessor } from 'solid-js'\r\n\r\ninterface PostData {\r\n  userId: number\r\n  id: number\r\n  title: string\r\n  body: string\r\n}\r\n\r\nexport default function Home() {\r\n  const [postId, setPostId] = createSignal(1)\r\n\r\n  return (\r\n    <main>\r\n      <Title>Solid Query v5</Title>\r\n      <h1>Solid Query v5</h1>\r\n      <p>\r\n        This is just a dev release for demo. Please dont use it in production\r\n        yet. Also this package will be deprecated as soon as features are live\r\n        on @tanstack/query\r\n      </p>\r\n      <div>\r\n        <button\r\n          onClick={() => {\r\n            setPostId((id) => (id === 1 ? 1 : id - 1))\r\n          }}\r\n        >\r\n          Previous Page\r\n        </button>\r\n        <button\r\n          onClick={() => {\r\n            setPostId((id) => (id === 100 ? 100 : id + 1))\r\n          }}\r\n        >\r\n          Next Page\r\n        </button>\r\n      </div>\r\n\r\n      <Suspense\r\n        fallback={<div style={{ 'margin-top': '20px' }}>Loading post...</div>}\r\n      >\r\n        <Posts postId={postId} />\r\n      </Suspense>\r\n    </main>\r\n  )\r\n}\r\n\r\nfunction Posts({ postId }: { postId: Accessor<number> }) {\r\n  const query = createQuery(() => ({\r\n    queryKey: ['posts', postId()],\r\n    staleTime: Infinity,\r\n    queryFn: async () => {\r\n      const response = await fetch(\r\n        'https://jsonplaceholder.typicode.com/posts/' + postId(),\r\n      ).then((res) => res.json())\r\n\r\n      // simulate extra latency to make things like streaming behavior more clear\r\n      await new Promise((r) => setTimeout(r, 1000))\r\n\r\n      return [response] as PostData[]\r\n    },\r\n  }))\r\n\r\n  return (\r\n    <For each={query.data}>\r\n      {(post) => (\r\n        <div>\r\n          <h3>{post.title}</h3>\r\n          <p>{post.body}</p>\r\n        </div>\r\n      )}\r\n    </For>\r\n  )\r\n}\r\n```",
        "pr_file_module": null
      },
      {
        "comment_id": "1070075612",
        "repo_full_name": "TanStack/query",
        "pr_number": 4803,
        "pr_file": "examples/solid/solid-start/src/routes/index.tsx",
        "discussion_id": "1069858512",
        "commented_code": "@@ -0,0 +1,63 @@\n+import { Title } from 'solid-start'\n+import { createQuery, useQueryClient } from '@tanstack/solid-query'\n+import { createSignal, For, Suspense } from 'solid-js'\n+import { isServer } from 'solid-js/web'\n+\n+interface PostData {\n+  userId: number\n+  id: number\n+  title: string\n+  body: string\n+}\n+\n+export default function Home() {\n+  const [postId, setPostId] = createSignal(1)\n+\n+  const query = createQuery(() => ({\n+    queryKey: ['posts', postId()],\n+    queryFn: async () => {\n+      const response = await fetch(\n+        'https://jsonplaceholder.typicode.com/posts/' + postId(),\n+      ).then((res) => res.json())\n+      return [response] as PostData[]\n+    },\n+  }))\n+\n+  return (\n+    <main>\n+      <Title>Solid Query v5</Title>\n+      <h1>Solid Query v5</h1>\n+      <p>\n+        This is just a dev release for demo. Please dont use it in production\n+        yet. Also this package will be deprecated as soon as features are live\n+        on @tanstack/query\n+      </p>\n+      <div>\n+        <button\n+          onClick={() => {\n+            setPostId((id) => (id === 1 ? 1 : id - 1))\n+          }}\n+        >\n+          Previous Page\n+        </button>\n+        <button\n+          onClick={() => {\n+            setPostId((id) => (id === 100 ? 100 : id + 1))\n+          }}\n+        >\n+          Next Page\n+        </button>\n+      </div>\n+      <Suspense>",
        "comment_created_at": "2023-01-13T21:22:01+00:00",
        "comment_author": "ardeora",
        "comment_body": "Yeah this was from when i was trying to futz around with Streaming SSR but could not figure it out haha. I'll fix the example to follow the above changes you requested!\r\n",
        "pr_file_module": null
      }
    ]
  },
  {
    "discussion_id": "2429866083",
    "pr_number": 9310,
    "pr_file": "packages/react-query/src/__tests__/useMutation.test.tsx",
    "created_at": "2025-10-14T16:59:21+00:00",
    "commented_code": "})\n \n   it('should be able to throw an error when useErrorBoundary is a function that returns true', async () => {\n-    let boundary = false\n+    let callBoundaryCount = 0",
    "repo_full_name": "TanStack/query",
    "discussion_comments": [
      {
        "comment_id": "2429866083",
        "repo_full_name": "TanStack/query",
        "pr_number": 9310,
        "pr_file": "packages/react-query/src/__tests__/useMutation.test.tsx",
        "discussion_id": "2429866083",
        "commented_code": "@@ -735,7 +735,7 @@ describe('useMutation', () => {\n   })\n \n   it('should be able to throw an error when useErrorBoundary is a function that returns true', async () => {\n-    let boundary = false\n+    let callBoundaryCount = 0",
        "comment_created_at": "2025-10-14T16:59:21+00:00",
        "comment_author": "gwansikk",
        "comment_body": "When `useErrorBoundary` is passed as a function to `useMutation`,\nin **React 19**, this function is called **three times**, and since the last call returns `false`,\nthe error is **not passed to the ErrorBoundary** but instead rendered inside the component.\n(In **React 18**, it was called **twice** and worked correctly.)\n\nDue to **React 19's changed render sequence**, the **React Query Observer** runs three times.\nTo fix this, we are updating the logic to a **count-based approach** that doesn't rely on render counts (i.e., not using `!boundary` logic).\n",
        "pr_file_module": null
      }
    ]
  },
  {
    "discussion_id": "2429869331",
    "pr_number": 9310,
    "pr_file": "packages/react-query/src/__tests__/useQueries.test.tsx",
    "created_at": "2025-10-14T17:00:39+00:00",
    "commented_code": "await waitFor(() => rendered.getByText('data1: 5, data2: 10'))\n     await waitFor(() => rendered.getByText('isFetching: false'))\n \n-    await waitFor(() => expect(states.length).toBe(6))\n-\n-    expect(states[0]).toMatchObject([\n-      {\n-        status: 'loading',\n-        data: undefined,\n-        isPreviousData: false,\n-        isFetching: true,\n-      },\n-      {\n-        status: 'loading',\n-        data: undefined,\n-        isPreviousData: false,\n-        isFetching: true,\n-      },\n-    ])\n-    expect(states[1]).toMatchObject([\n-      { status: 'success', data: 5, isPreviousData: false, isFetching: false },\n-      { status: 'success', data: 10, isPreviousData: false, isFetching: false },\n-    ])\n-    expect(states[2]).toMatchObject([\n-      { status: 'success', data: 10, isPreviousData: false, isFetching: false },\n-    ])\n-    expect(states[3]).toMatchObject([\n-      { status: 'success', data: 5, isPreviousData: false, isFetching: true },\n-      { status: 'success', data: 10, isPreviousData: false, isFetching: false },\n-    ])\n-    expect(states[4]).toMatchObject([\n-      { status: 'success', data: 5, isPreviousData: false, isFetching: true },\n-      { status: 'success', data: 10, isPreviousData: false, isFetching: false },\n-    ])\n-    expect(states[5]).toMatchObject([\n-      { status: 'success', data: 5, isPreviousData: false, isFetching: false },\n-      { status: 'success', data: 10, isPreviousData: false, isFetching: false },\n-    ])\n+    await waitFor(() =>\n+      expect(states.length).toBe(reactVersion() === '18' ? 6 : 7),\n+    )\n+\n+    if (reactVersion() === '18') {",
    "repo_full_name": "TanStack/query",
    "discussion_comments": [
      {
        "comment_id": "2429869331",
        "repo_full_name": "TanStack/query",
        "pr_number": 9310,
        "pr_file": "packages/react-query/src/__tests__/useQueries.test.tsx",
        "discussion_id": "2429869331",
        "commented_code": "@@ -281,41 +282,169 @@ describe('useQueries', () => {\n     await waitFor(() => rendered.getByText('data1: 5, data2: 10'))\n     await waitFor(() => rendered.getByText('isFetching: false'))\n \n-    await waitFor(() => expect(states.length).toBe(6))\n-\n-    expect(states[0]).toMatchObject([\n-      {\n-        status: 'loading',\n-        data: undefined,\n-        isPreviousData: false,\n-        isFetching: true,\n-      },\n-      {\n-        status: 'loading',\n-        data: undefined,\n-        isPreviousData: false,\n-        isFetching: true,\n-      },\n-    ])\n-    expect(states[1]).toMatchObject([\n-      { status: 'success', data: 5, isPreviousData: false, isFetching: false },\n-      { status: 'success', data: 10, isPreviousData: false, isFetching: false },\n-    ])\n-    expect(states[2]).toMatchObject([\n-      { status: 'success', data: 10, isPreviousData: false, isFetching: false },\n-    ])\n-    expect(states[3]).toMatchObject([\n-      { status: 'success', data: 5, isPreviousData: false, isFetching: true },\n-      { status: 'success', data: 10, isPreviousData: false, isFetching: false },\n-    ])\n-    expect(states[4]).toMatchObject([\n-      { status: 'success', data: 5, isPreviousData: false, isFetching: true },\n-      { status: 'success', data: 10, isPreviousData: false, isFetching: false },\n-    ])\n-    expect(states[5]).toMatchObject([\n-      { status: 'success', data: 5, isPreviousData: false, isFetching: false },\n-      { status: 'success', data: 10, isPreviousData: false, isFetching: false },\n-    ])\n+    await waitFor(() =>\n+      expect(states.length).toBe(reactVersion() === '18' ? 6 : 7),\n+    )\n+\n+    if (reactVersion() === '18') {",
        "comment_created_at": "2025-10-14T17:00:39+00:00",
        "comment_author": "gwansikk",
        "comment_body": "This part also has different state tests due to the changed render sequence in React 19.\nWe\u2019ve clearly separated the handling logic according to each React version.\n",
        "pr_file_module": null
      }
    ]
  },
  {
    "discussion_id": "2024257289",
    "pr_number": 8896,
    "pr_file": "packages/react-query/src/__tests__/useQuery.promise.test.tsx",
    "created_at": "2025-04-02T07:42:27+00:00",
    "commented_code": "},\n       })\n \n+      // Force Page to re-render when query state changes\n+      React.useEffect(() => {\n+        // noop\n+      }, [query.status])\n+",
    "repo_full_name": "TanStack/query",
    "discussion_comments": [
      {
        "comment_id": "2024257289",
        "repo_full_name": "TanStack/query",
        "pr_number": 8896,
        "pr_file": "packages/react-query/src/__tests__/useQuery.promise.test.tsx",
        "discussion_id": "2024257289",
        "commented_code": "@@ -59,6 +59,11 @@ describe('useQuery().promise', () => {\n         },\n       })\n \n+      // Force Page to re-render when query state changes\n+      React.useEffect(() => {\n+        // noop\n+      }, [query.status])\n+",
        "comment_created_at": "2025-04-02T07:42:27+00:00",
        "comment_author": "TkDodo",
        "comment_body": "why is this necessary ?",
        "pr_file_module": null
      },
      {
        "comment_id": "2024259793",
        "repo_full_name": "TanStack/query",
        "pr_number": 8896,
        "pr_file": "packages/react-query/src/__tests__/useQuery.promise.test.tsx",
        "discussion_id": "2024257289",
        "commented_code": "@@ -59,6 +59,11 @@ describe('useQuery().promise', () => {\n         },\n       })\n \n+      // Force Page to re-render when query state changes\n+      React.useEffect(() => {\n+        // noop\n+      }, [query.status])\n+",
        "comment_created_at": "2025-04-02T07:44:06+00:00",
        "comment_author": "birkskyum",
        "comment_body": "The below test with [Page, MyComponent] only had one element returned otherwise",
        "pr_file_module": null
      },
      {
        "comment_id": "2024277577",
        "repo_full_name": "TanStack/query",
        "pr_number": 8896,
        "pr_file": "packages/react-query/src/__tests__/useQuery.promise.test.tsx",
        "discussion_id": "2024257289",
        "commented_code": "@@ -59,6 +59,11 @@ describe('useQuery().promise', () => {\n         },\n       })\n \n+      // Force Page to re-render when query state changes\n+      React.useEffect(() => {\n+        // noop\n+      }, [query.status])\n+",
        "comment_created_at": "2025-04-02T07:54:53+00:00",
        "comment_author": "TkDodo",
        "comment_body": "would ist work if we\u2019d just render the status in a div instead:\r\n\r\n```\r\n<div>status: {query.status}</div>\r\n```",
        "pr_file_module": null
      },
      {
        "comment_id": "2024419143",
        "repo_full_name": "TanStack/query",
        "pr_number": 8896,
        "pr_file": "packages/react-query/src/__tests__/useQuery.promise.test.tsx",
        "discussion_id": "2024257289",
        "commented_code": "@@ -59,6 +59,11 @@ describe('useQuery().promise', () => {\n         },\n       })\n \n+      // Force Page to re-render when query state changes\n+      React.useEffect(() => {\n+        // noop\n+      }, [query.status])\n+",
        "comment_created_at": "2025-04-02T09:10:03+00:00",
        "comment_author": "birkskyum",
        "comment_body": "this is in a `describe('useQuery().promise', () => {` suite, so it probably becomes a redundant test if we don't use query.promise. I tried doing it just now, and the loading ends up as `status: pending` too if the promise isn't used",
        "pr_file_module": null
      },
      {
        "comment_id": "2024433823",
        "repo_full_name": "TanStack/query",
        "pr_number": 8896,
        "pr_file": "packages/react-query/src/__tests__/useQuery.promise.test.tsx",
        "discussion_id": "2024257289",
        "commented_code": "@@ -59,6 +59,11 @@ describe('useQuery().promise', () => {\n         },\n       })\n \n+      // Force Page to re-render when query state changes\n+      React.useEffect(() => {\n+        // noop\n+      }, [query.status])\n+",
        "comment_created_at": "2025-04-02T09:18:33+00:00",
        "comment_author": "TkDodo",
        "comment_body": "yeah I meant additionally, just instead of the effect",
        "pr_file_module": null
      },
      {
        "comment_id": "2024442817",
        "repo_full_name": "TanStack/query",
        "pr_number": 8896,
        "pr_file": "packages/react-query/src/__tests__/useQuery.promise.test.tsx",
        "discussion_id": "2024257289",
        "commented_code": "@@ -59,6 +59,11 @@ describe('useQuery().promise', () => {\n         },\n       })\n \n+      // Force Page to re-render when query state changes\n+      React.useEffect(() => {\n+        // noop\n+      }, [query.status])\n+",
        "comment_created_at": "2025-04-02T09:23:42+00:00",
        "comment_author": "birkskyum",
        "comment_body": "Ah, that works",
        "pr_file_module": null
      }
    ]
  },
  {
    "discussion_id": "1650702028",
    "pr_number": 7582,
    "pr_file": "packages/react-query/src/__tests__/prefetch.test.tsx",
    "created_at": "2024-06-24T09:41:57+00:00",
    "commented_code": "+import { describe, expect, it, vi } from 'vitest'\n+import React from 'react'\n+import { fireEvent, waitFor } from '@testing-library/react'\n+import { ErrorBoundary } from 'react-error-boundary'\n+import {\n+  QueryCache,\n+  usePrefetchInfiniteQuery,\n+  usePrefetchQuery,\n+  useQueryErrorResetBoundary,\n+  useSuspenseInfiniteQuery,\n+  useSuspenseQuery,\n+} from '..'\n+import { createQueryClient, queryKey, renderWithClient, sleep } from './utils'\n+\n+import type { InfiniteData, UseInfiniteQueryOptions, UseQueryOptions } from '..'\n+import type { Mock } from 'vitest'\n+\n+const generateQueryFn = (data: string) =>\n+  vi.fn<any, Promise<string>>().mockImplementation(async () => {\n+    await sleep(10)\n+\n+    return data\n+  })\n+\n+const generateInfiniteQueryOptions = (\n+  data: Array<{ data: string; currentPage: number; totalPages: number }>,\n+) => {\n+  let currentPage = 0\n+\n+  return {\n+    queryFn: vi\n+      .fn<any, Promise<(typeof data)[number]>>()\n+      .mockImplementation(async () => {\n+        const currentPageData = data[currentPage]\n+        if (!currentPageData) {\n+          throw new Error('No data defined for page ' + currentPage)\n+        }\n+\n+        await sleep(10)\n+        currentPage++\n+\n+        return currentPageData\n+      }),\n+    initialPageParam: 1,\n+    getNextPageParam: (lastPage: (typeof data)[number]) =>\n+      lastPage.currentPage === lastPage.totalPages\n+        ? undefined\n+        : lastPage.currentPage + 1,\n+  }\n+}\n+\n+describe('usePrefetchQuery', () => {\n+  const queryCache = new QueryCache()\n+  const queryClient = createQueryClient({ queryCache })\n+\n+  function Suspended<TData = unknown>(props: {\n+    queryOpts: UseQueryOptions<TData, Error, TData, Array<string>>\n+  }) {\n+    const state = useSuspenseQuery(props.queryOpts)\n+\n+    return (\n+      <div>\n+        <div>data: {String(state.data)}</div>\n+      </div>\n+    )\n+  }\n+\n+  it('should prefetch query if query state does not exist', async () => {\n+    const queryOpts = {\n+      queryKey: queryKey(),\n+      queryFn: generateQueryFn('Prefetch is nice!'),\n+    }\n+\n+    function App() {\n+      usePrefetchQuery(queryOpts)\n+\n+      return (\n+        <React.Suspense fallback=\"Loading...\">\n+          <Suspended queryOpts={queryOpts} />\n+        </React.Suspense>\n+      )\n+    }\n+\n+    const rendered = renderWithClient(queryClient, <App />)\n+\n+    await waitFor(() => rendered.getByText('data: Prefetch is nice!'))\n+    expect(queryOpts.queryFn).toHaveBeenCalledTimes(1)\n+  })\n+\n+  it('should not prefetch query if query state exists', async () => {\n+    const queryOpts = {\n+      queryKey: queryKey(),\n+      queryFn: generateQueryFn('The usePrefetchQuery hook is smart!'),\n+    }\n+\n+    function App() {\n+      usePrefetchQuery(queryOpts)\n+\n+      return (\n+        <React.Suspense fallback=\"Loading...\">\n+          <Suspended queryOpts={queryOpts} />\n+        </React.Suspense>\n+      )\n+    }\n+\n+    await queryClient.fetchQuery(queryOpts)\n+    ;(queryOpts.queryFn as Mock).mockClear()\n+    const rendered = renderWithClient(queryClient, <App />)\n+\n+    expect(rendered.queryByText('fetching: true')).not.toBeInTheDocument()\n+    await waitFor(() =>\n+      rendered.getByText('data: The usePrefetchQuery hook is smart!'),\n+    )\n+    expect(queryOpts.queryFn).not.toHaveBeenCalled()\n+  })\n+\n+  it('should display an error boundary if query cache is populated with an error', async () => {\n+    const queryFn = generateQueryFn('Not an error')\n+\n+    const queryOpts = {\n+      queryKey: queryKey(),\n+      queryFn,\n+    }\n+\n+    queryFn.mockImplementationOnce(async () => {\n+      await sleep(10)\n+\n+      throw new Error('Oops! Server error!')\n+    })\n+\n+    function App() {\n+      usePrefetchQuery(queryOpts)",
    "repo_full_name": "TanStack/query",
    "discussion_comments": [
      {
        "comment_id": "1650702028",
        "repo_full_name": "TanStack/query",
        "pr_number": 7582,
        "pr_file": "packages/react-query/src/__tests__/prefetch.test.tsx",
        "discussion_id": "1650702028",
        "commented_code": "@@ -0,0 +1,352 @@\n+import { describe, expect, it, vi } from 'vitest'\n+import React from 'react'\n+import { fireEvent, waitFor } from '@testing-library/react'\n+import { ErrorBoundary } from 'react-error-boundary'\n+import {\n+  QueryCache,\n+  usePrefetchInfiniteQuery,\n+  usePrefetchQuery,\n+  useQueryErrorResetBoundary,\n+  useSuspenseInfiniteQuery,\n+  useSuspenseQuery,\n+} from '..'\n+import { createQueryClient, queryKey, renderWithClient, sleep } from './utils'\n+\n+import type { InfiniteData, UseInfiniteQueryOptions, UseQueryOptions } from '..'\n+import type { Mock } from 'vitest'\n+\n+const generateQueryFn = (data: string) =>\n+  vi.fn<any, Promise<string>>().mockImplementation(async () => {\n+    await sleep(10)\n+\n+    return data\n+  })\n+\n+const generateInfiniteQueryOptions = (\n+  data: Array<{ data: string; currentPage: number; totalPages: number }>,\n+) => {\n+  let currentPage = 0\n+\n+  return {\n+    queryFn: vi\n+      .fn<any, Promise<(typeof data)[number]>>()\n+      .mockImplementation(async () => {\n+        const currentPageData = data[currentPage]\n+        if (!currentPageData) {\n+          throw new Error('No data defined for page ' + currentPage)\n+        }\n+\n+        await sleep(10)\n+        currentPage++\n+\n+        return currentPageData\n+      }),\n+    initialPageParam: 1,\n+    getNextPageParam: (lastPage: (typeof data)[number]) =>\n+      lastPage.currentPage === lastPage.totalPages\n+        ? undefined\n+        : lastPage.currentPage + 1,\n+  }\n+}\n+\n+describe('usePrefetchQuery', () => {\n+  const queryCache = new QueryCache()\n+  const queryClient = createQueryClient({ queryCache })\n+\n+  function Suspended<TData = unknown>(props: {\n+    queryOpts: UseQueryOptions<TData, Error, TData, Array<string>>\n+  }) {\n+    const state = useSuspenseQuery(props.queryOpts)\n+\n+    return (\n+      <div>\n+        <div>data: {String(state.data)}</div>\n+      </div>\n+    )\n+  }\n+\n+  it('should prefetch query if query state does not exist', async () => {\n+    const queryOpts = {\n+      queryKey: queryKey(),\n+      queryFn: generateQueryFn('Prefetch is nice!'),\n+    }\n+\n+    function App() {\n+      usePrefetchQuery(queryOpts)\n+\n+      return (\n+        <React.Suspense fallback=\"Loading...\">\n+          <Suspended queryOpts={queryOpts} />\n+        </React.Suspense>\n+      )\n+    }\n+\n+    const rendered = renderWithClient(queryClient, <App />)\n+\n+    await waitFor(() => rendered.getByText('data: Prefetch is nice!'))\n+    expect(queryOpts.queryFn).toHaveBeenCalledTimes(1)\n+  })\n+\n+  it('should not prefetch query if query state exists', async () => {\n+    const queryOpts = {\n+      queryKey: queryKey(),\n+      queryFn: generateQueryFn('The usePrefetchQuery hook is smart!'),\n+    }\n+\n+    function App() {\n+      usePrefetchQuery(queryOpts)\n+\n+      return (\n+        <React.Suspense fallback=\"Loading...\">\n+          <Suspended queryOpts={queryOpts} />\n+        </React.Suspense>\n+      )\n+    }\n+\n+    await queryClient.fetchQuery(queryOpts)\n+    ;(queryOpts.queryFn as Mock).mockClear()\n+    const rendered = renderWithClient(queryClient, <App />)\n+\n+    expect(rendered.queryByText('fetching: true')).not.toBeInTheDocument()\n+    await waitFor(() =>\n+      rendered.getByText('data: The usePrefetchQuery hook is smart!'),\n+    )\n+    expect(queryOpts.queryFn).not.toHaveBeenCalled()\n+  })\n+\n+  it('should display an error boundary if query cache is populated with an error', async () => {\n+    const queryFn = generateQueryFn('Not an error')\n+\n+    const queryOpts = {\n+      queryKey: queryKey(),\n+      queryFn,\n+    }\n+\n+    queryFn.mockImplementationOnce(async () => {\n+      await sleep(10)\n+\n+      throw new Error('Oops! Server error!')\n+    })\n+\n+    function App() {\n+      usePrefetchQuery(queryOpts)",
        "comment_created_at": "2024-06-24T09:41:57+00:00",
        "comment_author": "Ephem",
        "comment_body": "I _think_ to replicate the bug we saw with endless loops, the `usePrefetchQuery` would have to be inside the Suspense boundary so it would rerender->refetch when unsuspended? I haven't tested so not entirely sure though.",
        "pr_file_module": null
      },
      {
        "comment_id": "1651256252",
        "repo_full_name": "TanStack/query",
        "pr_number": 7582,
        "pr_file": "packages/react-query/src/__tests__/prefetch.test.tsx",
        "discussion_id": "1650702028",
        "commented_code": "@@ -0,0 +1,352 @@\n+import { describe, expect, it, vi } from 'vitest'\n+import React from 'react'\n+import { fireEvent, waitFor } from '@testing-library/react'\n+import { ErrorBoundary } from 'react-error-boundary'\n+import {\n+  QueryCache,\n+  usePrefetchInfiniteQuery,\n+  usePrefetchQuery,\n+  useQueryErrorResetBoundary,\n+  useSuspenseInfiniteQuery,\n+  useSuspenseQuery,\n+} from '..'\n+import { createQueryClient, queryKey, renderWithClient, sleep } from './utils'\n+\n+import type { InfiniteData, UseInfiniteQueryOptions, UseQueryOptions } from '..'\n+import type { Mock } from 'vitest'\n+\n+const generateQueryFn = (data: string) =>\n+  vi.fn<any, Promise<string>>().mockImplementation(async () => {\n+    await sleep(10)\n+\n+    return data\n+  })\n+\n+const generateInfiniteQueryOptions = (\n+  data: Array<{ data: string; currentPage: number; totalPages: number }>,\n+) => {\n+  let currentPage = 0\n+\n+  return {\n+    queryFn: vi\n+      .fn<any, Promise<(typeof data)[number]>>()\n+      .mockImplementation(async () => {\n+        const currentPageData = data[currentPage]\n+        if (!currentPageData) {\n+          throw new Error('No data defined for page ' + currentPage)\n+        }\n+\n+        await sleep(10)\n+        currentPage++\n+\n+        return currentPageData\n+      }),\n+    initialPageParam: 1,\n+    getNextPageParam: (lastPage: (typeof data)[number]) =>\n+      lastPage.currentPage === lastPage.totalPages\n+        ? undefined\n+        : lastPage.currentPage + 1,\n+  }\n+}\n+\n+describe('usePrefetchQuery', () => {\n+  const queryCache = new QueryCache()\n+  const queryClient = createQueryClient({ queryCache })\n+\n+  function Suspended<TData = unknown>(props: {\n+    queryOpts: UseQueryOptions<TData, Error, TData, Array<string>>\n+  }) {\n+    const state = useSuspenseQuery(props.queryOpts)\n+\n+    return (\n+      <div>\n+        <div>data: {String(state.data)}</div>\n+      </div>\n+    )\n+  }\n+\n+  it('should prefetch query if query state does not exist', async () => {\n+    const queryOpts = {\n+      queryKey: queryKey(),\n+      queryFn: generateQueryFn('Prefetch is nice!'),\n+    }\n+\n+    function App() {\n+      usePrefetchQuery(queryOpts)\n+\n+      return (\n+        <React.Suspense fallback=\"Loading...\">\n+          <Suspended queryOpts={queryOpts} />\n+        </React.Suspense>\n+      )\n+    }\n+\n+    const rendered = renderWithClient(queryClient, <App />)\n+\n+    await waitFor(() => rendered.getByText('data: Prefetch is nice!'))\n+    expect(queryOpts.queryFn).toHaveBeenCalledTimes(1)\n+  })\n+\n+  it('should not prefetch query if query state exists', async () => {\n+    const queryOpts = {\n+      queryKey: queryKey(),\n+      queryFn: generateQueryFn('The usePrefetchQuery hook is smart!'),\n+    }\n+\n+    function App() {\n+      usePrefetchQuery(queryOpts)\n+\n+      return (\n+        <React.Suspense fallback=\"Loading...\">\n+          <Suspended queryOpts={queryOpts} />\n+        </React.Suspense>\n+      )\n+    }\n+\n+    await queryClient.fetchQuery(queryOpts)\n+    ;(queryOpts.queryFn as Mock).mockClear()\n+    const rendered = renderWithClient(queryClient, <App />)\n+\n+    expect(rendered.queryByText('fetching: true')).not.toBeInTheDocument()\n+    await waitFor(() =>\n+      rendered.getByText('data: The usePrefetchQuery hook is smart!'),\n+    )\n+    expect(queryOpts.queryFn).not.toHaveBeenCalled()\n+  })\n+\n+  it('should display an error boundary if query cache is populated with an error', async () => {\n+    const queryFn = generateQueryFn('Not an error')\n+\n+    const queryOpts = {\n+      queryKey: queryKey(),\n+      queryFn,\n+    }\n+\n+    queryFn.mockImplementationOnce(async () => {\n+      await sleep(10)\n+\n+      throw new Error('Oops! Server error!')\n+    })\n+\n+    function App() {\n+      usePrefetchQuery(queryOpts)",
        "comment_created_at": "2024-06-24T15:46:16+00:00",
        "comment_author": "lopesrbruno",
        "comment_body": "@Ephem , I'm not sure, but this endless loops isn't about the usage of `ensureQueryData` instead of `prefetchQuery`? But I will add a test covering the usage of the hook inside the Suspense Boundary.",
        "pr_file_module": null
      },
      {
        "comment_id": "1651280012",
        "repo_full_name": "TanStack/query",
        "pr_number": 7582,
        "pr_file": "packages/react-query/src/__tests__/prefetch.test.tsx",
        "discussion_id": "1650702028",
        "commented_code": "@@ -0,0 +1,352 @@\n+import { describe, expect, it, vi } from 'vitest'\n+import React from 'react'\n+import { fireEvent, waitFor } from '@testing-library/react'\n+import { ErrorBoundary } from 'react-error-boundary'\n+import {\n+  QueryCache,\n+  usePrefetchInfiniteQuery,\n+  usePrefetchQuery,\n+  useQueryErrorResetBoundary,\n+  useSuspenseInfiniteQuery,\n+  useSuspenseQuery,\n+} from '..'\n+import { createQueryClient, queryKey, renderWithClient, sleep } from './utils'\n+\n+import type { InfiniteData, UseInfiniteQueryOptions, UseQueryOptions } from '..'\n+import type { Mock } from 'vitest'\n+\n+const generateQueryFn = (data: string) =>\n+  vi.fn<any, Promise<string>>().mockImplementation(async () => {\n+    await sleep(10)\n+\n+    return data\n+  })\n+\n+const generateInfiniteQueryOptions = (\n+  data: Array<{ data: string; currentPage: number; totalPages: number }>,\n+) => {\n+  let currentPage = 0\n+\n+  return {\n+    queryFn: vi\n+      .fn<any, Promise<(typeof data)[number]>>()\n+      .mockImplementation(async () => {\n+        const currentPageData = data[currentPage]\n+        if (!currentPageData) {\n+          throw new Error('No data defined for page ' + currentPage)\n+        }\n+\n+        await sleep(10)\n+        currentPage++\n+\n+        return currentPageData\n+      }),\n+    initialPageParam: 1,\n+    getNextPageParam: (lastPage: (typeof data)[number]) =>\n+      lastPage.currentPage === lastPage.totalPages\n+        ? undefined\n+        : lastPage.currentPage + 1,\n+  }\n+}\n+\n+describe('usePrefetchQuery', () => {\n+  const queryCache = new QueryCache()\n+  const queryClient = createQueryClient({ queryCache })\n+\n+  function Suspended<TData = unknown>(props: {\n+    queryOpts: UseQueryOptions<TData, Error, TData, Array<string>>\n+  }) {\n+    const state = useSuspenseQuery(props.queryOpts)\n+\n+    return (\n+      <div>\n+        <div>data: {String(state.data)}</div>\n+      </div>\n+    )\n+  }\n+\n+  it('should prefetch query if query state does not exist', async () => {\n+    const queryOpts = {\n+      queryKey: queryKey(),\n+      queryFn: generateQueryFn('Prefetch is nice!'),\n+    }\n+\n+    function App() {\n+      usePrefetchQuery(queryOpts)\n+\n+      return (\n+        <React.Suspense fallback=\"Loading...\">\n+          <Suspended queryOpts={queryOpts} />\n+        </React.Suspense>\n+      )\n+    }\n+\n+    const rendered = renderWithClient(queryClient, <App />)\n+\n+    await waitFor(() => rendered.getByText('data: Prefetch is nice!'))\n+    expect(queryOpts.queryFn).toHaveBeenCalledTimes(1)\n+  })\n+\n+  it('should not prefetch query if query state exists', async () => {\n+    const queryOpts = {\n+      queryKey: queryKey(),\n+      queryFn: generateQueryFn('The usePrefetchQuery hook is smart!'),\n+    }\n+\n+    function App() {\n+      usePrefetchQuery(queryOpts)\n+\n+      return (\n+        <React.Suspense fallback=\"Loading...\">\n+          <Suspended queryOpts={queryOpts} />\n+        </React.Suspense>\n+      )\n+    }\n+\n+    await queryClient.fetchQuery(queryOpts)\n+    ;(queryOpts.queryFn as Mock).mockClear()\n+    const rendered = renderWithClient(queryClient, <App />)\n+\n+    expect(rendered.queryByText('fetching: true')).not.toBeInTheDocument()\n+    await waitFor(() =>\n+      rendered.getByText('data: The usePrefetchQuery hook is smart!'),\n+    )\n+    expect(queryOpts.queryFn).not.toHaveBeenCalled()\n+  })\n+\n+  it('should display an error boundary if query cache is populated with an error', async () => {\n+    const queryFn = generateQueryFn('Not an error')\n+\n+    const queryOpts = {\n+      queryKey: queryKey(),\n+      queryFn,\n+    }\n+\n+    queryFn.mockImplementationOnce(async () => {\n+      await sleep(10)\n+\n+      throw new Error('Oops! Server error!')\n+    })\n+\n+    function App() {\n+      usePrefetchQuery(queryOpts)",
        "comment_created_at": "2024-06-24T16:03:45+00:00",
        "comment_author": "lopesrbruno",
        "comment_body": "Added new tests to ensure that endless loops don't occur at #7614 ",
        "pr_file_module": null
      }
    ]
  },
  {
    "discussion_id": "1468552220",
    "pr_number": 6753,
    "pr_file": "packages/react-query-next-experimental/src/HydrationStreamProvider.tsx",
    "created_at": "2024-01-27T18:47:09+00:00",
    "commented_code": "onEntriesRef.current = props.onEntries\n     })\n \n-    React.useEffect(() => {\n+    // Setup and run the onEntries handler on the client only, but do it during\n+    // the initial render so children have access to the data immediately\n+    // This is important to avoid the client suspending during the initial render\n+    // if the data has not yet been hydrated.",
    "repo_full_name": "TanStack/query",
    "discussion_comments": [
      {
        "comment_id": "1468552220",
        "repo_full_name": "TanStack/query",
        "pr_number": 6753,
        "pr_file": "packages/react-query-next-experimental/src/HydrationStreamProvider.tsx",
        "discussion_id": "1468552220",
        "commented_code": "@@ -143,31 +143,28 @@ export function createHydrationStreamProvider<TShape>() {\n       onEntriesRef.current = props.onEntries\n     })\n \n-    React.useEffect(() => {\n+    // Setup and run the onEntries handler on the client only, but do it during\n+    // the initial render so children have access to the data immediately\n+    // This is important to avoid the client suspending during the initial render\n+    // if the data has not yet been hydrated.",
        "comment_created_at": "2024-01-27T18:47:09+00:00",
        "comment_author": "Ephem",
        "comment_body": "I'm not super on top of the `react-query-next-experimental` library so not sure if use cases and edge cases align, but, I thought I'd note that it might be worth checking out this comment (and implementation) in the `HydrationBoundary` for how we handle hydration there: https://github.com/TanStack/query/blob/main/packages/react-query/src/HydrationBoundary.tsx#L35-L49\r\n\r\nShort version, what we do there is that if data is not already in the cache, we hydrate in render, if it is, we hydrate in an effect so we don't cause side effects inside of render.\r\n\r\nI'm not sure how likely this is to happen with the streaming library, if it can at all, but I thought I'd mention it.",
        "pr_file_module": null
      },
      {
        "comment_id": "1477429529",
        "repo_full_name": "TanStack/query",
        "pr_number": 6753,
        "pr_file": "packages/react-query-next-experimental/src/HydrationStreamProvider.tsx",
        "discussion_id": "1468552220",
        "commented_code": "@@ -143,31 +143,28 @@ export function createHydrationStreamProvider<TShape>() {\n       onEntriesRef.current = props.onEntries\n     })\n \n-    React.useEffect(() => {\n+    // Setup and run the onEntries handler on the client only, but do it during\n+    // the initial render so children have access to the data immediately\n+    // This is important to avoid the client suspending during the initial render\n+    // if the data has not yet been hydrated.",
        "comment_created_at": "2024-02-04T19:57:06+00:00",
        "comment_author": "mgreenw",
        "comment_body": "Interesting callout! I _think_ it's a different situation here, and what we're doing is safe. `HydrationBoundary` could happen at any part of the tree, whereas there will only be one `ReactQueryStreamedHydration` and it will be high up in the tree / wrapping the whole thing. This code will only be called once on boot, and we went any streamed data to be available ASAP on the initial render phase.\r\n\r\nDefinitely let me know if you see any problems with that logic!",
        "pr_file_module": null
      },
      {
        "comment_id": "1493385609",
        "repo_full_name": "TanStack/query",
        "pr_number": 6753,
        "pr_file": "packages/react-query-next-experimental/src/HydrationStreamProvider.tsx",
        "discussion_id": "1468552220",
        "commented_code": "@@ -143,31 +143,28 @@ export function createHydrationStreamProvider<TShape>() {\n       onEntriesRef.current = props.onEntries\n     })\n \n-    React.useEffect(() => {\n+    // Setup and run the onEntries handler on the client only, but do it during\n+    // the initial render so children have access to the data immediately\n+    // This is important to avoid the client suspending during the initial render\n+    // if the data has not yet been hydrated.",
        "comment_created_at": "2024-02-17T18:42:59+00:00",
        "comment_author": "TkDodo",
        "comment_body": "I also think the whole hydration can only happen once, on the first render, where the cache is still empty. I'd give this a go as-is.\r\n\r\nI added a small refactoring commit: https://github.com/TanStack/query/commit/bb512705de7b5b1e5825f288758e201fb719022c",
        "pr_file_module": null
      },
      {
        "comment_id": "1493755761",
        "repo_full_name": "TanStack/query",
        "pr_number": 6753,
        "pr_file": "packages/react-query-next-experimental/src/HydrationStreamProvider.tsx",
        "discussion_id": "1468552220",
        "commented_code": "@@ -143,31 +143,28 @@ export function createHydrationStreamProvider<TShape>() {\n       onEntriesRef.current = props.onEntries\n     })\n \n-    React.useEffect(() => {\n+    // Setup and run the onEntries handler on the client only, but do it during\n+    // the initial render so children have access to the data immediately\n+    // This is important to avoid the client suspending during the initial render\n+    // if the data has not yet been hydrated.",
        "comment_created_at": "2024-02-18T12:33:37+00:00",
        "comment_author": "mgreenw",
        "comment_body": "Thanks for taking this across the finish line @TkDodo!",
        "pr_file_module": null
      }
    ]
  },
  {
    "discussion_id": "1181013696",
    "pr_number": 5347,
    "pr_file": "packages/react-query-devtools/src/devtools.tsx",
    "created_at": "2023-04-29T08:00:43+00:00",
    "commented_code": "'use client'\n-import * as React from 'react'\n+import { useRef, useState, useEffect } from 'react'\n import type { QueryClient } from '@tanstack/react-query'\n-import useLocalStorage from './useLocalStorage'\n-import {\n-  isVerticalSide,\n-  useIsMounted,\n-  getSidePanelStyle,\n-  minPanelSize,\n-  getSidedProp,\n-  defaultPanelSize,\n-} from './utils'\n-import type { Corner, Side } from './utils'\n-import ScreenReader from './screenreader'\n-import { ThemeProvider, defaultTheme as theme } from './theme'\n-import Logo from './Logo'\n-\n-import type { DevToolsErrorType } from './types'\n-import ReactQueryDevtoolsPanel from './CachePanel/CachePanel'\n-\n-export { default as ReactQueryDevtoolsPanel } from './CachePanel/CachePanel'\n-\n+import { useQueryClient, onlineManager } from '@tanstack/react-query'\n+import type {\n+  DevtoolsButtonPosition,\n+  DevtoolsPosition,\n+} from '@tanstack/query-devtools'\n+import { TanstackQueryDevtools } from '@tanstack/query-devtools'\n+import React from 'react'\n export interface DevtoolsOptions {\n   /**\n    * Set this true if you want the dev tools to default to being open\n    */\n   initialIsOpen?: boolean\n-  /**\n-   * Use this to add props to the panel. For example, you can add className, style (merge and override default style), etc.\n-   */\n-  panelProps?: React.ComponentPropsWithoutRef<'div'>\n-  /**\n-   * Use this to add props to the close button. For example, you can add className, style (merge and override default style), onClick (extend default handler), etc.\n-   */\n-  closeButtonProps?: React.ComponentPropsWithoutRef<'button'>\n-  /**\n-   * Use this to add props to the toggle button. For example, you can add className, style (merge and override default style), onClick (extend default handler), etc.\n-   */\n-  toggleButtonProps?: React.ComponentPropsWithoutRef<'button'>\n   /**\n    * The position of the React Query logo to open and close the devtools panel.\n    * Defaults to 'bottom-left'.\n    */\n-  position?: Corner\n+  buttonPosition?: DevtoolsButtonPosition\n   /**\n    * The position of the React Query devtools panel.\n    * Defaults to 'bottom'.\n    */\n-  panelPosition?: Side\n-  /**\n-   * Use this to render the devtools inside a different type of container element for a11y purposes.\n-   * Any string which corresponds to a valid intrinsic JSX element is allowed.\n-   * Defaults to 'aside'.\n-   */\n-  containerElement?: string | any\n-  /**\n-   * nonce for style element for CSP\n-   */\n-  styleNonce?: string\n+  position?: DevtoolsPosition\n+\n   /**\n    * Custom instance of QueryClient\n    */\n-  queryClient?: QueryClient\n-  /**\n-   * Use this so you can define custom errors that can be shown in the devtools.\n-   */\n-  errorTypes?: DevToolsErrorType[]\n+  client?: QueryClient\n }\n \n-export function ReactQueryDevtools({\n-  initialIsOpen,\n-  panelProps = {},\n-  closeButtonProps = {},\n-  toggleButtonProps = {},\n-  position = 'bottom-left',\n-  containerElement: Container = 'aside',\n-  queryClient,\n-  styleNonce,\n-  panelPosition: initialPanelPosition = 'bottom',\n-  errorTypes = [],\n-}: DevtoolsOptions): React.ReactElement | null {\n-  const rootRef = React.useRef<HTMLDivElement>(null)\n-  const panelRef = React.useRef<HTMLDivElement>(null)\n-  const [isOpen, setIsOpen] = useLocalStorage(\n-    'reactQueryDevtoolsOpen',\n-    initialIsOpen,\n+export function ReactQueryDevtools(\n+  props: DevtoolsOptions,\n+): React.ReactElement | null {\n+  const queryClient = useQueryClient()\n+  const ref = useRef<HTMLDivElement>(null)\n+  const { buttonPosition, position, initialIsOpen } = props\n+  const [devtools] = useState(\n+    new TanstackQueryDevtools({",
    "repo_full_name": "TanStack/query",
    "discussion_comments": [
      {
        "comment_id": "1181013696",
        "repo_full_name": "TanStack/query",
        "pr_number": 5347,
        "pr_file": "packages/react-query-devtools/src/devtools.tsx",
        "discussion_id": "1181013696",
        "commented_code": "@@ -1,343 +1,77 @@\n 'use client'\n-import * as React from 'react'\n+import { useRef, useState, useEffect } from 'react'\n import type { QueryClient } from '@tanstack/react-query'\n-import useLocalStorage from './useLocalStorage'\n-import {\n-  isVerticalSide,\n-  useIsMounted,\n-  getSidePanelStyle,\n-  minPanelSize,\n-  getSidedProp,\n-  defaultPanelSize,\n-} from './utils'\n-import type { Corner, Side } from './utils'\n-import ScreenReader from './screenreader'\n-import { ThemeProvider, defaultTheme as theme } from './theme'\n-import Logo from './Logo'\n-\n-import type { DevToolsErrorType } from './types'\n-import ReactQueryDevtoolsPanel from './CachePanel/CachePanel'\n-\n-export { default as ReactQueryDevtoolsPanel } from './CachePanel/CachePanel'\n-\n+import { useQueryClient, onlineManager } from '@tanstack/react-query'\n+import type {\n+  DevtoolsButtonPosition,\n+  DevtoolsPosition,\n+} from '@tanstack/query-devtools'\n+import { TanstackQueryDevtools } from '@tanstack/query-devtools'\n+import React from 'react'\n export interface DevtoolsOptions {\n   /**\n    * Set this true if you want the dev tools to default to being open\n    */\n   initialIsOpen?: boolean\n-  /**\n-   * Use this to add props to the panel. For example, you can add className, style (merge and override default style), etc.\n-   */\n-  panelProps?: React.ComponentPropsWithoutRef<'div'>\n-  /**\n-   * Use this to add props to the close button. For example, you can add className, style (merge and override default style), onClick (extend default handler), etc.\n-   */\n-  closeButtonProps?: React.ComponentPropsWithoutRef<'button'>\n-  /**\n-   * Use this to add props to the toggle button. For example, you can add className, style (merge and override default style), onClick (extend default handler), etc.\n-   */\n-  toggleButtonProps?: React.ComponentPropsWithoutRef<'button'>\n   /**\n    * The position of the React Query logo to open and close the devtools panel.\n    * Defaults to 'bottom-left'.\n    */\n-  position?: Corner\n+  buttonPosition?: DevtoolsButtonPosition\n   /**\n    * The position of the React Query devtools panel.\n    * Defaults to 'bottom'.\n    */\n-  panelPosition?: Side\n-  /**\n-   * Use this to render the devtools inside a different type of container element for a11y purposes.\n-   * Any string which corresponds to a valid intrinsic JSX element is allowed.\n-   * Defaults to 'aside'.\n-   */\n-  containerElement?: string | any\n-  /**\n-   * nonce for style element for CSP\n-   */\n-  styleNonce?: string\n+  position?: DevtoolsPosition\n+\n   /**\n    * Custom instance of QueryClient\n    */\n-  queryClient?: QueryClient\n-  /**\n-   * Use this so you can define custom errors that can be shown in the devtools.\n-   */\n-  errorTypes?: DevToolsErrorType[]\n+  client?: QueryClient\n }\n \n-export function ReactQueryDevtools({\n-  initialIsOpen,\n-  panelProps = {},\n-  closeButtonProps = {},\n-  toggleButtonProps = {},\n-  position = 'bottom-left',\n-  containerElement: Container = 'aside',\n-  queryClient,\n-  styleNonce,\n-  panelPosition: initialPanelPosition = 'bottom',\n-  errorTypes = [],\n-}: DevtoolsOptions): React.ReactElement | null {\n-  const rootRef = React.useRef<HTMLDivElement>(null)\n-  const panelRef = React.useRef<HTMLDivElement>(null)\n-  const [isOpen, setIsOpen] = useLocalStorage(\n-    'reactQueryDevtoolsOpen',\n-    initialIsOpen,\n+export function ReactQueryDevtools(\n+  props: DevtoolsOptions,\n+): React.ReactElement | null {\n+  const queryClient = useQueryClient()\n+  const ref = useRef<HTMLDivElement>(null)\n+  const { buttonPosition, position, initialIsOpen } = props\n+  const [devtools] = useState(\n+    new TanstackQueryDevtools({",
        "comment_created_at": "2023-04-29T08:00:43+00:00",
        "comment_author": "TkDodo",
        "comment_body": "this should probably be a function:\r\n\r\n```\r\nuseState(() => new TanstackQueryDevtools(...))\r\n```",
        "pr_file_module": null
      },
      {
        "comment_id": "1181130353",
        "repo_full_name": "TanStack/query",
        "pr_number": 5347,
        "pr_file": "packages/react-query-devtools/src/devtools.tsx",
        "discussion_id": "1181013696",
        "commented_code": "@@ -1,343 +1,77 @@\n 'use client'\n-import * as React from 'react'\n+import { useRef, useState, useEffect } from 'react'\n import type { QueryClient } from '@tanstack/react-query'\n-import useLocalStorage from './useLocalStorage'\n-import {\n-  isVerticalSide,\n-  useIsMounted,\n-  getSidePanelStyle,\n-  minPanelSize,\n-  getSidedProp,\n-  defaultPanelSize,\n-} from './utils'\n-import type { Corner, Side } from './utils'\n-import ScreenReader from './screenreader'\n-import { ThemeProvider, defaultTheme as theme } from './theme'\n-import Logo from './Logo'\n-\n-import type { DevToolsErrorType } from './types'\n-import ReactQueryDevtoolsPanel from './CachePanel/CachePanel'\n-\n-export { default as ReactQueryDevtoolsPanel } from './CachePanel/CachePanel'\n-\n+import { useQueryClient, onlineManager } from '@tanstack/react-query'\n+import type {\n+  DevtoolsButtonPosition,\n+  DevtoolsPosition,\n+} from '@tanstack/query-devtools'\n+import { TanstackQueryDevtools } from '@tanstack/query-devtools'\n+import React from 'react'\n export interface DevtoolsOptions {\n   /**\n    * Set this true if you want the dev tools to default to being open\n    */\n   initialIsOpen?: boolean\n-  /**\n-   * Use this to add props to the panel. For example, you can add className, style (merge and override default style), etc.\n-   */\n-  panelProps?: React.ComponentPropsWithoutRef<'div'>\n-  /**\n-   * Use this to add props to the close button. For example, you can add className, style (merge and override default style), onClick (extend default handler), etc.\n-   */\n-  closeButtonProps?: React.ComponentPropsWithoutRef<'button'>\n-  /**\n-   * Use this to add props to the toggle button. For example, you can add className, style (merge and override default style), onClick (extend default handler), etc.\n-   */\n-  toggleButtonProps?: React.ComponentPropsWithoutRef<'button'>\n   /**\n    * The position of the React Query logo to open and close the devtools panel.\n    * Defaults to 'bottom-left'.\n    */\n-  position?: Corner\n+  buttonPosition?: DevtoolsButtonPosition\n   /**\n    * The position of the React Query devtools panel.\n    * Defaults to 'bottom'.\n    */\n-  panelPosition?: Side\n-  /**\n-   * Use this to render the devtools inside a different type of container element for a11y purposes.\n-   * Any string which corresponds to a valid intrinsic JSX element is allowed.\n-   * Defaults to 'aside'.\n-   */\n-  containerElement?: string | any\n-  /**\n-   * nonce for style element for CSP\n-   */\n-  styleNonce?: string\n+  position?: DevtoolsPosition\n+\n   /**\n    * Custom instance of QueryClient\n    */\n-  queryClient?: QueryClient\n-  /**\n-   * Use this so you can define custom errors that can be shown in the devtools.\n-   */\n-  errorTypes?: DevToolsErrorType[]\n+  client?: QueryClient\n }\n \n-export function ReactQueryDevtools({\n-  initialIsOpen,\n-  panelProps = {},\n-  closeButtonProps = {},\n-  toggleButtonProps = {},\n-  position = 'bottom-left',\n-  containerElement: Container = 'aside',\n-  queryClient,\n-  styleNonce,\n-  panelPosition: initialPanelPosition = 'bottom',\n-  errorTypes = [],\n-}: DevtoolsOptions): React.ReactElement | null {\n-  const rootRef = React.useRef<HTMLDivElement>(null)\n-  const panelRef = React.useRef<HTMLDivElement>(null)\n-  const [isOpen, setIsOpen] = useLocalStorage(\n-    'reactQueryDevtoolsOpen',\n-    initialIsOpen,\n+export function ReactQueryDevtools(\n+  props: DevtoolsOptions,\n+): React.ReactElement | null {\n+  const queryClient = useQueryClient()\n+  const ref = useRef<HTMLDivElement>(null)\n+  const { buttonPosition, position, initialIsOpen } = props\n+  const [devtools] = useState(\n+    new TanstackQueryDevtools({",
        "comment_created_at": "2023-04-29T21:26:01+00:00",
        "comment_author": "ardeora",
        "comment_body": "Ah my bad! My brain is breaking switching my react brain on and off \ud83d\ude06 ",
        "pr_file_module": null
      }
    ]
  }
]