[
  {
    "discussion_id": "1874740799",
    "pr_number": 1764,
    "pr_file": "javascript/package.json",
    "created_at": "2024-12-08T10:51:44+00:00",
    "commented_code": "\"files\": [\n     \"dist/binaries/**\",\n     \"dist/src/**\",\n-    \"src/**\"\n+    \"src/**\",\n+    \"load.js\",\n+    \"load.js.map\"",
    "repo_full_name": "facebook/yoga",
    "discussion_comments": [
      {
        "comment_id": "1874740799",
        "repo_full_name": "facebook/yoga",
        "pr_number": 1764,
        "pr_file": "javascript/package.json",
        "discussion_id": "1874740799",
        "commented_code": "@@ -19,7 +19,9 @@\n   \"files\": [\n     \"dist/binaries/**\",\n     \"dist/src/**\",\n-    \"src/**\"\n+    \"src/**\",\n+    \"load.js\",\n+    \"load.js.map\"",
        "comment_created_at": "2024-12-08T10:51:44+00:00",
        "comment_author": "NickGerleman",
        "comment_body": "I think this is missing `load.d.ts`\r\n\r\nconsider including `load.*` (or whatever the right glob is to allow any extension)",
        "pr_file_module": null
      },
      {
        "comment_id": "1875715786",
        "repo_full_name": "facebook/yoga",
        "pr_number": 1764,
        "pr_file": "javascript/package.json",
        "discussion_id": "1874740799",
        "commented_code": "@@ -19,7 +19,9 @@\n   \"files\": [\n     \"dist/binaries/**\",\n     \"dist/src/**\",\n-    \"src/**\"\n+    \"src/**\",\n+    \"load.js\",\n+    \"load.js.map\"",
        "comment_created_at": "2024-12-09T10:13:58+00:00",
        "comment_author": "nyan-left",
        "comment_body": "Missed a commit, thanks for spotting this. ",
        "pr_file_module": null
      }
    ]
  },
  {
    "discussion_id": "92471048",
    "pr_number": 283,
    "pr_file": "csharp/Facebook.Yoga/project.json",
    "created_at": "2016-12-14T19:35:24+00:00",
    "commented_code": "-{\n-  \"language\": \"en\",\n-  \"version\": \"3.0.0-*\",\n-\n+\ufeff{\n   \"dependencies\": {\n+    \"Microsoft.NETCore.Portable.Compatibility\": \"1.0.1\",\n     \"NETStandard.Library\": \"1.6.0\"\n   },\n-\n   \"frameworks\": {\n-    \"netstandard1.6\": {\n-      \"imports\": \"dnxcore50\"\n-    }\n-  }\n-}\n+    \"netstandard1.1\": {}",
    "repo_full_name": "facebook/yoga",
    "discussion_comments": [
      {
        "comment_id": "92471048",
        "repo_full_name": "facebook/yoga",
        "pr_number": 283,
        "pr_file": "csharp/Facebook.Yoga/project.json",
        "discussion_id": "92471048",
        "commented_code": "@@ -1,14 +1,12 @@\n-{\n-  \"language\": \"en\",\n-  \"version\": \"3.0.0-*\",\n-\n+\ufeff{\n   \"dependencies\": {\n+    \"Microsoft.NETCore.Portable.Compatibility\": \"1.0.1\",\n     \"NETStandard.Library\": \"1.6.0\"\n   },\n-\n   \"frameworks\": {\n-    \"netstandard1.6\": {\n-      \"imports\": \"dnxcore50\"\n-    }\n-  }\n-}\n+    \"netstandard1.1\": {}",
        "comment_created_at": "2016-12-14T19:35:24+00:00",
        "comment_author": "pre10der89",
        "comment_body": "NETStandard 1.1 is the minimum that can be used with DLLImport",
        "pr_file_module": null
      }
    ]
  }
]